{
  "indexes": [
    {
      "collectionGroup": "runs",
      "queryScope": "COLLECTION_GROUP",
      "fields": [
        {
          "fieldPath": "assigningOrgs.classes",
          "arrayConfig": "CONTAINS"
        },
        {
          "fieldPath": "taskId",
          "order": "ASCENDING"
        }
      ]
    },
    {
      "collectionGroup": "runs",
      "queryScope": "COLLECTION_GROUP",
      "fields": [
        {
          "fieldPath": "assigningOrgs.districts",
          "arrayConfig": "CONTAINS"
        },
        {
          "fieldPath": "taskId",
          "order": "ASCENDING"
        }
      ]
    },
    {
      "collectionGroup": "runs",
      "queryScope": "COLLECTION_GROUP",
      "fields": [
        {
          "fieldPath": "assigningOrgs.groups",
          "arrayConfig": "CONTAINS"
        },
        {
          "fieldPath": "taskId",
          "order": "ASCENDING"
        }
      ]
    },
    {
      "collectionGroup": "runs",
      "queryScope": "COLLECTION_GROUP",
      "fields": [
        {
          "fieldPath": "assigningOrgs.schools",
          "arrayConfig": "CONTAINS"
        },
        {
          "fieldPath": "taskId",
          "order": "ASCENDING"
        }
      ]
    },
    {
      "collectionGroup": "runs",
      "queryScope": "COLLECTION_GROUP",
      "fields": [
        {
          "fieldPath": "completed",
          "order": "ASCENDING"
        },
        {
          "fieldPath": "taskId",
          "order": "ASCENDING"
        }
      ]
    },
    {
      "collectionGroup": "runs",
      "queryScope": "COLLECTION_GROUP",
      "fields": [
        {
          "fieldPath": "taskId",
          "order": "ASCENDING"
        },
        {
          "fieldPath": "variantId",
          "order": "ASCENDING"
        }
      ]
    },
    {
      "collectionGroup": "variants",
      "queryScope": "COLLECTION",
      "fields": [
        {
          "fieldPath": "params",
          "order": "ASCENDING"
        },
        {
          "fieldPath": "lastUpdated",
          "order": "ASCENDING"
        }
      ]
    },
    {
      "collectionGroup": "variants",
      "queryScope": "COLLECTION",
      "fields": [
        {
          "fieldPath": "params",
          "order": "ASCENDING"
        },
        {
          "fieldPath": "lastUpdated",
          "order": "DESCENDING"
        }
      ]
    }
  ],
  "fieldOverrides": [
    {
      "collectionGroup": "runs",
      "fieldPath": "assigningOrgs.classes",
      "ttl": false,
      "indexes": [
        {
          "order": "ASCENDING",
          "queryScope": "COLLECTION"
        },
        {
          "order": "DESCENDING",
          "queryScope": "COLLECTION"
        },
        {
          "arrayConfig": "CONTAINS",
          "queryScope": "COLLECTION"
        },
        {
          "arrayConfig": "CONTAINS",
          "queryScope": "COLLECTION_GROUP"
        }
      ]
    },
    {
      "collectionGroup": "runs",
      "fieldPath": "assigningOrgs.districts",
      "ttl": false,
      "indexes": [
        {
          "order": "ASCENDING",
          "queryScope": "COLLECTION"
        },
        {
          "order": "DESCENDING",
          "queryScope": "COLLECTION"
        },
        {
          "arrayConfig": "CONTAINS",
          "queryScope": "COLLECTION"
        },
        {
          "arrayConfig": "CONTAINS",
          "queryScope": "COLLECTION_GROUP"
        }
      ]
    },
    {
      "collectionGroup": "runs",
      "fieldPath": "assigningOrgs.groups",
      "ttl": false,
      "indexes": [
        {
          "order": "ASCENDING",
          "queryScope": "COLLECTION"
        },
        {
          "order": "DESCENDING",
          "queryScope": "COLLECTION"
        },
        {
          "arrayConfig": "CONTAINS",
          "queryScope": "COLLECTION"
        },
        {
          "arrayConfig": "CONTAINS",
          "queryScope": "COLLECTION_GROUP"
        }
      ]
    },
    {
      "collectionGroup": "runs",
      "fieldPath": "assigningOrgs.schools",
      "ttl": false,
      "indexes": [
        {
          "order": "ASCENDING",
          "queryScope": "COLLECTION"
        },
        {
          "order": "DESCENDING",
          "queryScope": "COLLECTION"
        },
        {
          "arrayConfig": "CONTAINS",
          "queryScope": "COLLECTION"
        },
        {
          "arrayConfig": "CONTAINS",
          "queryScope": "COLLECTION_GROUP"
        }
      ]
    },
    {
      "collectionGroup": "runs",
      "fieldPath": "completed",
      "ttl": false,
      "indexes": [
        {
          "order": "ASCENDING",
          "queryScope": "COLLECTION"
        },
        {
          "order": "DESCENDING",
          "queryScope": "COLLECTION"
        },
        {
          "arrayConfig": "CONTAINS",
          "queryScope": "COLLECTION"
        },
        {
          "order": "DESCENDING",
          "queryScope": "COLLECTION_GROUP"
        },
        {
          "arrayConfig": "CONTAINS",
          "queryScope": "COLLECTION_GROUP"
        }
      ]
    },
    {
      "collectionGroup": "runs",
      "fieldPath": "id",
      "ttl": false,
      "indexes": [
        {
          "order": "ASCENDING",
          "queryScope": "COLLECTION"
        },
        {
          "order": "DESCENDING",
          "queryScope": "COLLECTION"
        },
        {
          "arrayConfig": "CONTAINS",
          "queryScope": "COLLECTION"
        },
        {
          "order": "ASCENDING",
          "queryScope": "COLLECTION_GROUP"
        },
        {
          "arrayConfig": "CONTAINS",
          "queryScope": "COLLECTION_GROUP"
        }
      ]
    },
    {
      "collectionGroup": "runs",
      "fieldPath": "taskId",
      "ttl": false,
      "indexes": [
        {
          "order": "ASCENDING",
          "queryScope": "COLLECTION"
        },
        {
          "order": "DESCENDING",
          "queryScope": "COLLECTION"
        },
        {
          "arrayConfig": "CONTAINS",
          "queryScope": "COLLECTION"
        },
        {
          "order": "ASCENDING",
          "queryScope": "COLLECTION_GROUP"
        }
      ]
    },
    {
      "collectionGroup": "runs",
      "fieldPath": "variantId",
      "ttl": false,
      "indexes": [
        {
          "order": "ASCENDING",
          "queryScope": "COLLECTION"
        },
        {
          "order": "DESCENDING",
          "queryScope": "COLLECTION"
        },
        {
          "arrayConfig": "CONTAINS",
          "queryScope": "COLLECTION"
        },
        {
          "order": "ASCENDING",
          "queryScope": "COLLECTION_GROUP"
        }
      ]
    }
  ]
}
